{
  "signals": [
    {
      "symbol": "IBM",
      "signal": "SELL",
      "score": -0.65,
      "confidence": 0.75,
      "price": 229.57,
      "change_pct": -8.8502,
      "vol_ratio": 1.59,
      "source": "standalone_momentum_v4.1",
      "session": "us_regular",
      "ts": "2026-04-23T16:00:12.523636+00:00",
      "final_score": 0.719,
      "features": {
        "price_change_pct": 0.0885,
        "volume_ratio": 1.59,
        "momentum_score": 0.65,
        "confidence": 0.75,
        "session_weight": 0.1
      }
    },
    {
      "symbol": "NOW",
      "signal": "SELL",
      "score": -0.65,
      "confidence": 0.75,
      "price": 85.35,
      "change_pct": -17.1922,
      "vol_ratio": 1.68,
      "source": "standalone_momentum_v4.1",
      "session": "us_regular",
      "ts": "2026-04-23T16:00:12.523925+00:00",
      "final_score": 0.728,
      "features": {
        "price_change_pct": 0.1719,
        "volume_ratio": 1.68,
        "momentum_score": 0.65,
        "confidence": 0.75,
        "session_weight": 0.1
      }
    },
    {
      "symbol": "ACN",
      "signal": "SELL",
      "score": -0.65,
      "confidence": 0.65,
      "price": 176.84,
      "change_pct": -6.9753,
      "vol_ratio": 0.75,
      "source": "standalone_momentum_v4.1",
      "session": "us_regular",
      "ts": "2026-04-23T16:00:12.523077+00:00",
      "final_score": 0.595,
      "features": {
        "price_change_pct": 0.0698,
        "volume_ratio": 0.75,
        "momentum_score": 0.65,
        "confidence": 0.65,
        "session_weight": 0.1
      }
    },
    {
      "symbol": "ADBE",
      "signal": "SELL",
      "score": -0.65,
      "confidence": 0.65,
      "price": 236.77,
      "change_pct": -7.49,
      "vol_ratio": 0.96,
      "source": "standalone_momentum_v4.1",
      "session": "us_regular",
      "ts": "2026-04-23T16:00:12.523086+00:00",
      "final_score": 0.616,
      "features": {
        "price_change_pct": 0.0749,
        "volume_ratio": 0.96,
        "momentum_score": 0.65,
        "confidence": 0.65,
        "session_weight": 0.1
      }
    },
    {
      "symbol": "AFRM",
      "signal": "SELL",
      "score": -0.65,
      "confidence": 0.65,
      "price": 63.375,
      "change_pct": -4.8138,
      "vol_ratio": 0.35,
      "source": "standalone_momentum_v4.1",
      "session": "us_regular",
      "ts": "2026-04-23T16:00:12.523101+00:00",
      "final_score": 0.555,
      "features": {
        "price_change_pct": 0.0481,
        "volume_ratio": 0.35,
        "momentum_score": 0.65,
        "confidence": 0.65,
        "session_weight": 0.1
      }
    }
  ],
  "n_signals": 5,
  "universe_size": 386,
  "session": "us_regular",
  "model_info": {
    "type": "momentum_deterministic",
    "lookback_days": 5,
    "auc": null,
    "pos_rate": 0.0
  },
  "source": "standalone_momentum_v4.1",
  "updated_at": "2026-04-23T16:00:12.533446+00:00",
  "pushed_at": "2026-04-23T16:00:19.652286+00:00"
}