{
  "ibkr_connected": true,
  "trading_mode": "paper",
  "account": "DUM895161",
  "netliq": 880884.94,
  "available_cash": 23093.69,
  "stats": {
    "executed": 6,
    "failed": 3,
    "skipped": 1,
    "dry_run": 0
  },
  "order_locks": {
    "BIIB": 300.0,
    "GOOGL": 299.0,
    "QCOM": 296.0,
    "NEM": 295.0,
    "T": 294.0,
    "TXN": 291.0
  },
  "exit_queue_size": 0,
  "regular_queue_size": 0,
  "source": "execution_agent_v5.0",
  "updated_at": "2026-05-07T11:45:58.623494+00:00",
  "version": "5.0"
}