{
  "ibkr_connected": false,
  "trading_mode": "paper",
  "account": "DUM895161",
  "netliq": 754533.31,
  "available_cash": 393571.88,
  "stats": {
    "executed": 4213,
    "failed": 1657,
    "skipped": 326,
    "dry_run": 101
  },
  "order_locks": {
    "QCOM": 300.0,
    "NKE": 300.0,
    "MELI": 0.0,
    "V": 300.0,
    "COST": 300.0,
    "CORZ": 300.0,
    "WMT": 300.0,
    "JNJ": 300.0,
    "LMT": 300.0,
    "ROST": 300.0
  },
  "exit_queue_size": 0,
  "regular_queue_size": 490,
  "source": "execution_agent_v5.0",
  "updated_at": "2026-05-09T18:50:58.151304+00:00",
  "version": "5.0"
}