{
  "account": "DUM895161",
  "net_liquidation": 806309.88,
  "total_value": 806309.88,
  "cash_value": -6023040.28,
  "cash_pct": -7.4699,
  "buying_power": 0.0,
  "available_funds": -863609.81,
  "unrealized_pnl": 0.0,
  "gross_pos_val": 10070580.0,
  "n_positions": 131,
  "positions": {
    "WMT": {
      "shares": 659.0,
      "market_value": 86240.8,
      "avg_cost": 130.8121,
      "mkt_price": 130.8662,
      "unrealized_pnl": 35.6,
      "currency": "USD",
      "conid": 13824
    },
    "VEEV": {
      "shares": -662.0,
      "market_value": -109241.17,
      "avg_cost": 164.1012,
      "mkt_price": 165.0169,
      "unrealized_pnl": -606.15,
      "currency": "USD",
      "conid": 136254493
    },
    "ZM": {
      "shares": 948.0,
      "market_value": 102194.4,
      "avg_cost": 108.6599,
      "mkt_price": 107.8,
      "unrealized_pnl": -815.2,
      "currency": "USD",
      "conid": 361181057
    },
    "C": {
      "shares": 134.0,
      "market_value": 17448.67,
      "avg_cost": 129.6919,
      "mkt_price": 130.214,
      "unrealized_pnl": 69.95,
      "currency": "USD",
      "conid": 87335484
    },
    "CRM": {
      "shares": 327.0,
      "market_value": 58355.35,
      "avg_cost": 180.7731,
      "mkt_price": 178.4567,
      "unrealized_pnl": -757.45,
      "currency": "USD",
      "conid": 29624264
    },
    "TSLA": {
      "shares": -242.0,
      "market_value": -101405.26,
      "avg_cost": 417.7575,
      "mkt_price": 419.03,
      "unrealized_pnl": -307.94,
      "currency": "USD",
      "conid": 76792991
    },
    "JNJ": {
      "shares": 657.0,
      "market_value": 146451.87,
      "avg_cost": 223.2152,
      "mkt_price": 222.91,
      "unrealized_pnl": -200.53,
      "currency": "USD",
      "conid": 8719
    },
    "AON": {
      "shares": 371.0,
      "market_value": 116118.84,
      "avg_cost": 314.4972,
      "mkt_price": 312.9888,
      "unrealized_pnl": -559.61,
      "currency": "USD",
      "conid": 414366114
    },
    "PLD": {
      "shares": 1056.0,
      "market_value": 150793.18,
      "avg_cost": 143.3747,
      "mkt_price": 142.7966,
      "unrealized_pnl": -610.55,
      "currency": "USD",
      "conid": 88819288
    },
    "WDAY": {
      "shares": 196.0,
      "market_value": 24488.24,
      "avg_cost": 132.5873,
      "mkt_price": 124.94,
      "unrealized_pnl": -1498.88,
      "currency": "USD",
      "conid": 115324104
    },
    "FTNT": {
      "shares": -296.0,
      "market_value": -31883.72,
      "avg_cost": 107.2746,
      "mkt_price": 107.7153,
      "unrealized_pnl": -130.44,
      "currency": "USD",
      "conid": 70236214
    },
    "ARE": {
      "shares": 200.0,
      "market_value": 9175.11,
      "avg_cost": 45.9623,
      "mkt_price": 45.8756,
      "unrealized_pnl": -17.35,
      "currency": "USD",
      "conid": 6607487
    },
    "MRNA": {
      "shares": 470.0,
      "market_value": 23155.83,
      "avg_cost": 49.305,
      "mkt_price": 49.2677,
      "unrealized_pnl": -17.53,
      "currency": "USD",
      "conid": 344809106
    },
    "EQIX": {
      "shares": 9.0,
      "market_value": 9639.14,
      "avg_cost": 1080.1111,
      "mkt_price": 1071.0153,
      "unrealized_pnl": -81.86,
      "currency": "USD",
      "conid": 181764593
    },
    "TGT": {
      "shares": 1194.0,
      "market_value": 152369.83,
      "avg_cost": 128.0117,
      "mkt_price": 127.6129,
      "unrealized_pnl": -476.17,
      "currency": "USD",
      "conid": 6437
    },
    "VZ": {
      "shares": -3529.0,
      "market_value": -167062.85,
      "avg_cost": 47.2737,
      "mkt_price": 47.34,
      "unrealized_pnl": -233.87,
      "currency": "USD",
      "conid": 4901
    },
    "AMD": {
      "shares": 112.0,
      "market_value": 47254.41,
      "avg_cost": 420.3341,
      "mkt_price": 421.9144,
      "unrealized_pnl": 176.99,
      "currency": "USD",
      "conid": 4391
    },
    "QSR": {
      "shares": 324.0,
      "market_value": 25835.76,
      "avg_cost": 79.9954,
      "mkt_price": 79.74,
      "unrealized_pnl": -82.76,
      "currency": "USD",
      "conid": 176372132
    },
    "SYK": {
      "shares": 620.0,
      "market_value": 183338.3,
      "avg_cost": 296.1715,
      "mkt_price": 295.7069,
      "unrealized_pnl": -288.0,
      "currency": "USD",
      "conid": 4430948
    },
    "TXN": {
      "shares": 71.0,
      "market_value": 20584.45,
      "avg_cost": 291.3882,
      "mkt_price": 289.9219,
      "unrealized_pnl": -104.11,
      "currency": "USD",
      "conid": 13096
    },
    "DHR": {
      "shares": 366.0,
      "market_value": 64269.28,
      "avg_cost": 175.6664,
      "mkt_price": 175.5991,
      "unrealized_pnl": -24.62,
      "currency": "USD",
      "conid": 6442
    },
    "ADBE": {
      "shares": 764.0,
      "market_value": 192010.09,
      "avg_cost": 252.3495,
      "mkt_price": 251.3221,
      "unrealized_pnl": -784.95,
      "currency": "USD",
      "conid": 265768
    },
    "IQ": {
      "shares": 3625.0,
      "market_value": 4422.5,
      "avg_cost": 1.235,
      "mkt_price": 1.22,
      "unrealized_pnl": -54.39,
      "currency": "USD",
      "conid": 312029611
    },
    "PLTR": {
      "shares": 1144.0,
      "market_value": 155061.85,
      "avg_cost": 135.4619,
      "mkt_price": 135.5436,
      "unrealized_pnl": 93.39,
      "currency": "USD",
      "conid": 444857009
    },
    "BP": {
      "shares": 980.0,
      "market_value": 42973.0,
      "avg_cost": 43.865,
      "mkt_price": 43.85,
      "unrealized_pnl": -14.7,
      "currency": "USD",
      "conid": 5171
    },
    "NKE": {
      "shares": 1192.0,
      "market_value": 52483.76,
      "avg_cost": 44.2822,
      "mkt_price": 44.03,
      "unrealized_pnl": -300.64,
      "currency": "USD",
      "conid": 10291
    },
    "DIS": {
      "shares": 81.0,
      "market_value": 8833.59,
      "avg_cost": 108.5623,
      "mkt_price": 109.0566,
      "unrealized_pnl": 40.04,
      "currency": "USD",
      "conid": 6459
    },
    "HUM": {
      "shares": 100.0,
      "market_value": 24941.67,
      "avg_cost": 250.59,
      "mkt_price": 249.4167,
      "unrealized_pnl": -117.33,
      "currency": "USD",
      "conid": 8251
    },
    "UPST": {
      "shares": 1836.0,
      "market_value": 54671.94,
      "avg_cost": 29.7666,
      "mkt_price": 29.7777,
      "unrealized_pnl": 20.39,
      "currency": "USD",
      "conid": 460492620
    },
    "ENPH": {
      "shares": 462.0,
      "market_value": 16579.22,
      "avg_cost": 35.195,
      "mkt_price": 35.8858,
      "unrealized_pnl": 319.13,
      "currency": "USD",
      "conid": 105368327
    },
    "CRWD": {
      "shares": 247.0,
      "market_value": 123962.58,
      "avg_cost": 501.7196,
      "mkt_price": 501.8728,
      "unrealized_pnl": 37.84,
      "currency": "USD",
      "conid": 370757467
    },
    "INTU": {
      "shares": 21.0,
      "market_value": 8329.44,
      "avg_cost": 406.6376,
      "mkt_price": 396.64,
      "unrealized_pnl": -209.95,
      "currency": "USD",
      "conid": 270662
    },
    "ICE": {
      "shares": 433.0,
      "market_value": 67591.65,
      "avg_cost": 157.0139,
      "mkt_price": 156.1008,
      "unrealized_pnl": -395.35,
      "currency": "USD",
      "conid": 136370275
    },
    "TMO": {
      "shares": 215.0,
      "market_value": 100355.72,
      "avg_cost": 468.1515,
      "mkt_price": 466.7708,
      "unrealized_pnl": -296.85,
      "currency": "USD",
      "conid": 12869
    },
    "TWLO": {
      "shares": 45.0,
      "market_value": 8824.31,
      "avg_cost": 197.0122,
      "mkt_price": 196.0958,
      "unrealized_pnl": -41.24,
      "currency": "USD",
      "conid": 237794430
    },
    "BKNG": {
      "shares": 345.0,
      "market_value": 58096.37,
      "avg_cost": 169.1229,
      "mkt_price": 168.3953,
      "unrealized_pnl": -251.02,
      "currency": "USD",
      "conid": 308728373
    },
    "PENN": {
      "shares": 982.0,
      "market_value": 16576.73,
      "avg_cost": 16.9453,
      "mkt_price": 16.8806,
      "unrealized_pnl": -63.51,
      "currency": "USD",
      "conid": 4816415
    },
    "TCEHY": {
      "shares": 272.0,
      "market_value": 16415.2,
      "avg_cost": 60.8874,
      "mkt_price": 60.35,
      "unrealized_pnl": -146.16,
      "currency": "USD",
      "conid": 55279376
    },
    "CPB": {
      "shares": 300.0,
      "market_value": 6330.0,
      "avg_cost": 21.145,
      "mkt_price": 21.1,
      "unrealized_pnl": -13.5,
      "currency": "USD",
      "conid": 5980
    },
    "MELI": {
      "shares": -3.0,
      "market_value": -4990.11,
      "avg_cost": 1660.9756,
      "mkt_price": 1663.3704,
      "unrealized_pnl": -7.18,
      "currency": "USD",
      "conid": 45602025
    },
    "OKTA": {
      "shares": 688.0,
      "market_value": 54888.99,
      "avg_cost": 80.7923,
      "mkt_price": 79.7805,
      "unrealized_pnl": -696.12,
      "currency": "USD",
      "conid": 272356196
    },
    "ELV": {
      "shares": 191.0,
      "market_value": 71723.99,
      "avg_cost": 376.5214,
      "mkt_price": 375.5182,
      "unrealized_pnl": -191.6,
      "currency": "USD",
      "conid": 173962302
    },
    "NET": {
      "shares": 112.0,
      "market_value": 24428.83,
      "avg_cost": 255.199,
      "mkt_price": 218.1146,
      "unrealized_pnl": -4153.46,
      "currency": "USD",
      "conid": 382633646
    },
    "COST": {
      "shares": 191.0,
      "market_value": 193254.73,
      "avg_cost": 1011.7305,
      "mkt_price": 1011.8049,
      "unrealized_pnl": 14.21,
      "currency": "USD",
      "conid": 272997
    },
    "APA": {
      "shares": 1891.0,
      "market_value": 68367.96,
      "avg_cost": 36.3435,
      "mkt_price": 36.1544,
      "unrealized_pnl": -357.65,
      "currency": "USD",
      "conid": 474515500
    },
    "V": {
      "shares": 617.0,
      "market_value": 197612.76,
      "avg_cost": 320.9823,
      "mkt_price": 320.28,
      "unrealized_pnl": -433.33,
      "currency": "USD",
      "conid": 49462172
    },
    "CLOV": {
      "shares": 28889.0,
      "market_value": 81466.98,
      "avg_cost": 2.8245,
      "mkt_price": 2.82,
      "unrealized_pnl": -130.59,
      "currency": "USD",
      "conid": 464040647
    },
    "CI": {
      "shares": 71.0,
      "market_value": 20227.63,
      "avg_cost": 285.3154,
      "mkt_price": 284.8961,
      "unrealized_pnl": -29.76,
      "currency": "USD",
      "conid": 346403540
    },
    "HUBS": {
      "shares": 36.0,
      "market_value": 6637.36,
      "avg_cost": 247.4878,
      "mkt_price": 184.3711,
      "unrealized_pnl": -2272.2,
      "currency": "USD",
      "conid": 169544810
    },
    "ZS": {
      "shares": 477.0,
      "market_value": 70594.56,
      "avg_cost": 151.8891,
      "mkt_price": 147.997,
      "unrealized_pnl": -1856.56,
      "currency": "USD",
      "conid": 310621426
    },
    "RUN": {
      "shares": 3303.0,
      "market_value": 47365.11,
      "avg_cost": 14.1835,
      "mkt_price": 14.34,
      "unrealized_pnl": 517.07,
      "currency": "USD",
      "conid": 202225016
    },
    "AAPL": {
      "shares": 245.0,
      "market_value": 71368.5,
      "avg_cost": 291.1939,
      "mkt_price": 291.3,
      "unrealized_pnl": 26.0,
      "currency": "USD",
      "conid": 265598
    },
    "AI": {
      "shares": -856.0,
      "market_value": -7947.64,
      "avg_cost": 9.2599,
      "mkt_price": 9.2846,
      "unrealized_pnl": -21.12,
      "currency": "USD",
      "conid": 459113767
    },
    "CORZ": {
      "shares": 590.0,
      "market_value": 13570.0,
      "avg_cost": 23.045,
      "mkt_price": 23.0,
      "unrealized_pnl": -26.55,
      "currency": "USD",
      "conid": 679998205
    },
    "DPZ": {
      "shares": 547.0,
      "market_value": 182502.99,
      "avg_cost": 334.9811,
      "mkt_price": 333.6435,
      "unrealized_pnl": -731.66,
      "currency": "USD",
      "conid": 29831612
    },
    "SHOP": {
      "shares": 1217.0,
      "market_value": 134524.26,
      "avg_cost": 110.4166,
      "mkt_price": 110.5376,
      "unrealized_pnl": 147.21,
      "currency": "USD",
      "conid": 195014116
    },
    "LMT": {
      "shares": 42.0,
      "market_value": 21378.54,
      "avg_cost": 510.5676,
      "mkt_price": 509.0129,
      "unrealized_pnl": -65.3,
      "currency": "USD",
      "conid": 611191
    },
    "NOW": {
      "shares": 700.0,
      "market_value": 63122.77,
      "avg_cost": 90.984,
      "mkt_price": 90.1754,
      "unrealized_pnl": -566.05,
      "currency": "USD",
      "conid": 109911821
    },
    "SKLZ": {
      "shares": 1287.0,
      "market_value": 8877.44,
      "avg_cost": 6.9083,
      "mkt_price": 6.8978,
      "unrealized_pnl": -13.58,
      "currency": "USD",
      "conid": 636678518
    },
    "COP": {
      "shares": 473.0,
      "market_value": 54267.29,
      "avg_cost": 115.0927,
      "mkt_price": 114.73,
      "unrealized_pnl": -171.55,
      "currency": "USD",
      "conid": 10885
    },
    "UPS": {
      "shares": 84.0,
      "market_value": 8450.15,
      "avg_cost": 100.3219,
      "mkt_price": 100.597,
      "unrealized_pnl": 23.11,
      "currency": "USD",
      "conid": 6231002
    },
    "TTE": {
      "shares": 923.0,
      "market_value": 82091.62,
      "avg_cost": 88.9577,
      "mkt_price": 88.94,
      "unrealized_pnl": -16.35,
      "currency": "USD",
      "conid": 837140579
    },
    "APD": {
      "shares": 40.0,
      "market_value": 11842.96,
      "avg_cost": 298.025,
      "mkt_price": 296.074,
      "unrealized_pnl": -78.04,
      "currency": "USD",
      "conid": 4487
    },
    "GLOB": {
      "shares": 1020.0,
      "market_value": 40957.56,
      "avg_cost": 40.3859,
      "mkt_price": 40.1545,
      "unrealized_pnl": -236.11,
      "currency": "USD",
      "conid": 160756766
    },
    "QCOM": {
      "shares": 460.0,
      "market_value": 96362.54,
      "avg_cost": 210.6388,
      "mkt_price": 209.4838,
      "unrealized_pnl": -531.32,
      "currency": "USD",
      "conid": 273544
    },
    "CVS": {
      "shares": 194.0,
      "market_value": 17154.17,
      "avg_cost": 86.6303,
      "mkt_price": 88.4236,
      "unrealized_pnl": 347.89,
      "currency": "USD",
      "conid": 2585769
    },
    "RARE": {
      "shares": 521.0,
      "market_value": 13674.75,
      "avg_cost": 26.4034,
      "mkt_price": 26.2471,
      "unrealized_pnl": -81.44,
      "currency": "USD",
      "conid": 143541504
    },
    "PATH": {
      "shares": 2082.0,
      "market_value": 22152.48,
      "avg_cost": 10.8446,
      "mkt_price": 10.64,
      "unrealized_pnl": -425.97,
      "currency": "USD",
      "conid": 483311199
    },
    "BSX": {
      "shares": 2861.0,
      "market_value": 160959.86,
      "avg_cost": 56.483,
      "mkt_price": 56.26,
      "unrealized_pnl": -637.95,
      "currency": "USD",
      "conid": 5270
    },
    "BA": {
      "shares": -181.0,
      "market_value": -42596.54,
      "avg_cost": 233.8989,
      "mkt_price": 235.34,
      "unrealized_pnl": -260.83,
      "currency": "USD",
      "conid": 4762
    },
    "VNET": {
      "shares": 1194.0,
      "market_value": 10883.96,
      "avg_cost": 9.105,
      "mkt_price": 9.1155,
      "unrealized_pnl": 12.59,
      "currency": "USD",
      "conid": 87356334
    },
    "CHTR": {
      "shares": 559.0,
      "market_value": 89657.45,
      "avg_cost": 160.2018,
      "mkt_price": 160.389,
      "unrealized_pnl": 104.63,
      "currency": "USD",
      "conid": 233674866
    },
    "RIOT": {
      "shares": 1860.0,
      "market_value": 44472.6,
      "avg_cost": 24.2948,
      "mkt_price": 23.91,
      "unrealized_pnl": -715.77,
      "currency": "USD",
      "conid": 292830677
    },
    "CLX": {
      "shares": 623.0,
      "market_value": 57403.26,
      "avg_cost": 92.3597,
      "mkt_price": 92.1401,
      "unrealized_pnl": -136.83,
      "currency": "USD",
      "conid": 5794
    },
    "FATE": {
      "shares": 21180.0,
      "market_value": 51467.4,
      "avg_cost": 2.4139,
      "mkt_price": 2.43,
      "unrealized_pnl": 341.95,
      "currency": "USD",
      "conid": 134609575
    },
    "MDB": {
      "shares": 48.0,
      "market_value": 13890.17,
      "avg_cost": 291.7034,
      "mkt_price": 289.3784,
      "unrealized_pnl": -111.6,
      "currency": "USD",
      "conid": 292833239
    },
    "NIO": {
      "shares": 4220.0,
      "market_value": 25235.6,
      "avg_cost": 5.9283,
      "mkt_price": 5.98,
      "unrealized_pnl": 218.06,
      "currency": "USD",
      "conid": 332794741
    },
    "AA": {
      "shares": 300.0,
      "market_value": 19118.62,
      "avg_cost": 63.3317,
      "mkt_price": 63.7287,
      "unrealized_pnl": 119.12,
      "currency": "USD",
      "conid": 251962528
    },
    "ORCL": {
      "shares": 46.0,
      "market_value": 8839.7,
      "avg_cost": 194.3717,
      "mkt_price": 192.1675,
      "unrealized_pnl": -101.4,
      "currency": "USD",
      "conid": 272800
    },
    "GM": {
      "shares": 354.0,
      "market_value": 28052.41,
      "avg_cost": 79.2813,
      "mkt_price": 79.2441,
      "unrealized_pnl": -13.17,
      "currency": "USD",
      "conid": 80986742
    },
    "SNOW": {
      "shares": 1099.0,
      "market_value": 163738.42,
      "avg_cost": 149.0087,
      "mkt_price": 148.9886,
      "unrealized_pnl": -22.1,
      "currency": "USD",
      "conid": 444884769
    },
    "NVAX": {
      "shares": 9468.0,
      "market_value": 89283.24,
      "avg_cost": 9.3964,
      "mkt_price": 9.43,
      "unrealized_pnl": 317.89,
      "currency": "USD",
      "conid": 365598061
    },
    "CCI": {
      "shares": 1293.0,
      "market_value": 117768.62,
      "avg_cost": 91.2607,
      "mkt_price": 91.0817,
      "unrealized_pnl": -231.42,
      "currency": "USD",
      "conid": 176571182
    },
    "SLB": {
      "shares": 2869.0,
      "market_value": 151818.37,
      "avg_cost": 52.9665,
      "mkt_price": 52.9168,
      "unrealized_pnl": -142.64,
      "currency": "USD",
      "conid": 12200
    },
    "BIIB": {
      "shares": 44.0,
      "market_value": 8371.34,
      "avg_cost": 190.1827,
      "mkt_price": 190.2578,
      "unrealized_pnl": 3.3,
      "currency": "USD",
      "conid": 26734397
    },
    "RSG": {
      "shares": 49.0,
      "market_value": 9953.94,
      "avg_cost": 203.7204,
      "mkt_price": 203.1416,
      "unrealized_pnl": -28.36,
      "currency": "USD",
      "conid": 6478024
    },
    "YUM": {
      "shares": 121.0,
      "market_value": 19070.56,
      "avg_cost": 158.7365,
      "mkt_price": 157.6079,
      "unrealized_pnl": -136.56,
      "currency": "USD",
      "conid": 3206042
    },
    "DG": {
      "shares": 284.0,
      "market_value": 33085.63,
      "avg_cost": 117.2817,
      "mkt_price": 116.4987,
      "unrealized_pnl": -222.37,
      "currency": "USD",
      "conid": 70212228
    },
    "CDNS": {
      "shares": 70.0,
      "market_value": 24953.64,
      "avg_cost": 357.2356,
      "mkt_price": 356.4805,
      "unrealized_pnl": -52.85,
      "currency": "USD",
      "conid": 5552
    },
    "O": {
      "shares": 500.0,
      "market_value": 31210.0,
      "avg_cost": 62.432,
      "mkt_price": 62.42,
      "unrealized_pnl": -6.0,
      "currency": "USD",
      "conid": 10672
    },
    "DDOG": {
      "shares": 589.0,
      "market_value": 110153.29,
      "avg_cost": 187.1587,
      "mkt_price": 187.0175,
      "unrealized_pnl": -83.19,
      "currency": "USD",
      "conid": 383858515
    },
    "MA": {
      "shares": -80.0,
      "market_value": -39949.6,
      "avg_cost": 499.3645,
      "mkt_price": 499.37,
      "unrealized_pnl": -0.44,
      "currency": "USD",
      "conid": 38685693
    },
    "MPC": {
      "shares": 227.0,
      "market_value": 54989.27,
      "avg_cost": 242.2864,
      "mkt_price": 242.2435,
      "unrealized_pnl": -9.75,
      "currency": "USD",
      "conid": 89495776
    },
    "ABNB": {
      "shares": 23.0,
      "market_value": 3216.17,
      "avg_cost": 139.9999,
      "mkt_price": 139.8335,
      "unrealized_pnl": -3.83,
      "currency": "USD",
      "conid": 459530964
    },
    "SBUX": {
      "shares": 377.0,
      "market_value": 39480.8,
      "avg_cost": 104.8845,
      "mkt_price": 104.7236,
      "unrealized_pnl": -60.67,
      "currency": "USD",
      "conid": 274105
    },
    "NEM": {
      "shares": 73.0,
      "market_value": 8420.96,
      "avg_cost": 114.0037,
      "mkt_price": 115.3556,
      "unrealized_pnl": 98.69,
      "currency": "USD",
      "conid": 10174
    },
    "GIS": {
      "shares": 254.0,
      "market_value": 9047.01,
      "avg_cost": 35.745,
      "mkt_price": 35.6182,
      "unrealized_pnl": -32.22,
      "currency": "USD",
      "conid": 7616
    },
    "MCD": {
      "shares": -145.0,
      "market_value": -41373.12,
      "avg_cost": 285.4401,
      "mkt_price": 285.3319,
      "unrealized_pnl": 15.7,
      "currency": "USD",
      "conid": 9408
    },
    "GRAB": {
      "shares": -2544.0,
      "market_value": -9463.68,
      "avg_cost": 3.7048,
      "mkt_price": 3.72,
      "unrealized_pnl": -38.73,
      "currency": "USD",
      "conid": 530319709
    },
    "TMUS": {
      "shares": -350.0,
      "market_value": -68110.0,
      "avg_cost": 194.0185,
      "mkt_price": 194.6,
      "unrealized_pnl": -203.53,
      "currency": "USD",
      "conid": 125980227
    },
    "ACAD": {
      "shares": 2432.0,
      "market_value": 54975.41,
      "avg_cost": 22.58,
      "mkt_price": 22.605,
      "unrealized_pnl": 60.74,
      "currency": "USD",
      "conid": 29308796
    },
    "AWK": {
      "shares": 200.0,
      "market_value": 25292.95,
      "avg_cost": 127.365,
      "mkt_price": 126.4648,
      "unrealized_pnl": -180.05,
      "currency": "USD",
      "conid": 50530752
    },
    "ENR": {
      "shares": 200.0,
      "market_value": 3724.15,
      "avg_cost": 18.7175,
      "mkt_price": 18.6207,
      "unrealized_pnl": -19.35,
      "currency": "USD",
      "conid": 196610672
    },
    "LLY": {
      "shares": 56.0,
      "market_value": 54615.12,
      "avg_cost": 975.0493,
      "mkt_price": 975.27,
      "unrealized_pnl": 12.36,
      "currency": "USD",
      "conid": 9160
    },
    "META": {
      "shares": 203.0,
      "market_value": 124627.79,
      "avg_cost": 614.3429,
      "mkt_price": 613.93,
      "unrealized_pnl": -83.82,
      "currency": "USD",
      "conid": 107113386
    },
    "NVDA": {
      "shares": 1023.0,
      "market_value": 218364.59,
      "avg_cost": 213.1738,
      "mkt_price": 213.4551,
      "unrealized_pnl": 287.79,
      "currency": "USD",
      "conid": 4815747
    },
    "HAL": {
      "shares": 1871.0,
      "market_value": 73474.17,
      "avg_cost": 39.4093,
      "mkt_price": 39.27,
      "unrealized_pnl": -260.6,
      "currency": "USD",
      "conid": 7890
    },
    "MU": {
      "shares": 56.0,
      "market_value": 38221.32,
      "avg_cost": 683.27,
      "mkt_price": 682.5236,
      "unrealized_pnl": -41.8,
      "currency": "USD",
      "conid": 9939
    },
    "PANW": {
      "shares": 7.0,
      "market_value": 1368.56,
      "avg_cost": 196.3922,
      "mkt_price": 195.5079,
      "unrealized_pnl": -6.19,
      "currency": "USD",
      "conid": 110619459
    },
    "CNC": {
      "shares": 125.0,
      "market_value": 6884.33,
      "avg_cost": 55.448,
      "mkt_price": 55.0746,
      "unrealized_pnl": -46.67,
      "currency": "USD",
      "conid": 13878278
    },
    "DOCU": {
      "shares": 499.0,
      "market_value": 23504.62,
      "avg_cost": 47.9078,
      "mkt_price": 47.1034,
      "unrealized_pnl": -401.39,
      "currency": "USD",
      "conid": 316073742
    },
    "UNH": {
      "shares": 598.0,
      "market_value": 223465.23,
      "avg_cost": 372.8444,
      "mkt_price": 373.6877,
      "unrealized_pnl": 504.28,
      "currency": "USD",
      "conid": 13272
    },
    "MSFT": {
      "shares": 459.0,
      "market_value": 190618.11,
      "avg_cost": 416.4094,
      "mkt_price": 415.29,
      "unrealized_pnl": -513.82,
      "currency": "USD",
      "conid": 272093
    },
    "RTX": {
      "shares": 122.0,
      "market_value": 21501.1,
      "avg_cost": 176.5664,
      "mkt_price": 176.2386,
      "unrealized_pnl": -40.0,
      "currency": "USD",
      "conid": 415342104
    },
    "PSX": {
      "shares": 230.0,
      "market_value": 38675.41,
      "avg_cost": 168.2589,
      "mkt_price": 168.154,
      "unrealized_pnl": -24.13,
      "currency": "USD",
      "conid": 105669270
    },
    "CMCSA": {
      "shares": 1854.0,
      "market_value": 48477.7,
      "avg_cost": 26.1915,
      "mkt_price": 26.1476,
      "unrealized_pnl": -81.35,
      "currency": "USD",
      "conid": 267748
    },
    "HUT": {
      "shares": 542.0,
      "market_value": 55666.08,
      "avg_cost": 106.0538,
      "mkt_price": 102.7049,
      "unrealized_pnl": -1815.06,
      "currency": "USD",
      "conid": 669228291
    },
    "ABT": {
      "shares": 199.0,
      "market_value": 17313.06,
      "avg_cost": 87.2948,
      "mkt_price": 87.0003,
      "unrealized_pnl": -58.6,
      "currency": "USD",
      "conid": 4065
    },
    "AFRM": {
      "shares": 2842.0,
      "market_value": 196240.11,
      "avg_cost": 68.5209,
      "mkt_price": 69.05,
      "unrealized_pnl": 1503.82,
      "currency": "USD",
      "conid": 465119069
    },
    "PYPL": {
      "shares": 3102.0,
      "market_value": 142475.18,
      "avg_cost": 45.9721,
      "mkt_price": 45.9301,
      "unrealized_pnl": -130.29,
      "currency": "USD",
      "conid": 199169591
    },
    "DT": {
      "shares": 1539.0,
      "market_value": 61313.75,
      "avg_cost": 40.0961,
      "mkt_price": 39.84,
      "unrealized_pnl": -394.2,
      "currency": "USD",
      "conid": 376427905
    },
    "TS": {
      "shares": 3672.0,
      "market_value": 218973.76,
      "avg_cost": 59.5934,
      "mkt_price": 59.6334,
      "unrealized_pnl": 146.68,
      "currency": "USD",
      "conid": 16675601
    },
    "DKNG": {
      "shares": 4160.0,
      "market_value": 111469.99,
      "avg_cost": 26.8336,
      "mkt_price": 26.7957,
      "unrealized_pnl": -157.75,
      "currency": "USD",
      "conid": 560105364
    },
    "OPEN": {
      "shares": 3200.0,
      "market_value": 17280.0,
      "avg_cost": 5.3778,
      "mkt_price": 5.4,
      "unrealized_pnl": 71.19,
      "currency": "USD",
      "conid": 460320153
    },
    "VTEX": {
      "shares": 4214.0,
      "market_value": 16478.05,
      "avg_cost": 4.1587,
      "mkt_price": 3.9103,
      "unrealized_pnl": -1046.71,
      "currency": "USD",
      "conid": 503299590
    },
    "ACHR": {
      "shares": 1296.0,
      "market_value": 8115.05,
      "avg_cost": 6.325,
      "mkt_price": 6.2616,
      "unrealized_pnl": -82.16,
      "currency": "USD",
      "conid": 514640214
    },
    "HD": {
      "shares": -149.0,
      "market_value": -48212.13,
      "avg_cost": 323.043,
      "mkt_price": 323.5713,
      "unrealized_pnl": -78.72,
      "currency": "USD",
      "conid": 7930
    },
    "ALB": {
      "shares": 421.0,
      "market_value": 84823.84,
      "avg_cost": 201.8546,
      "mkt_price": 201.4818,
      "unrealized_pnl": -156.94,
      "currency": "USD",
      "conid": 4347
    },
    "ARWR": {
      "shares": 722.0,
      "market_value": 55620.3,
      "avg_cost": 78.1093,
      "mkt_price": 77.0364,
      "unrealized_pnl": -774.62,
      "currency": "USD",
      "conid": 228571236
    },
    "CTSH": {
      "shares": 3291.0,
      "market_value": 168927.04,
      "avg_cost": 51.7609,
      "mkt_price": 51.33,
      "unrealized_pnl": -1417.96,
      "currency": "USD",
      "conid": 4728759
    },
    "ISRG": {
      "shares": -133.0,
      "market_value": -60483.08,
      "avg_cost": 452.6741,
      "mkt_price": 454.76,
      "unrealized_pnl": -277.42,
      "currency": "USD",
      "conid": 9063285
    }
  },
  "timestamp": "2026-05-08T13:30:45.952539+00:00",
  "source": "ibeam_rest_v5.0.4"
}