{
  "history": [
    {
      "ts": "2026-05-19T15:02:51.161986+00:00",
      "label": "C21",
      "total_pnl": -5933.09,
      "n_positions": 52,
      "sharpe": 0.0,
      "drawdown": 0.0,
      "win_rate": 0.0
    },
    {
      "ts": "2026-05-19T15:03:51.160594+00:00",
      "label": "C22",
      "total_pnl": -5256.06,
      "n_positions": 52,
      "sharpe": 0.0,
      "drawdown": 0.0,
      "win_rate": 0.0
    },
    {
      "ts": "2026-05-19T15:04:51.162137+00:00",
      "label": "C23",
      "total_pnl": -4374.89,
      "n_positions": 52,
      "sharpe": 0.0,
      "drawdown": 0.0,
      "win_rate": 0.0
    },
    {
      "ts": "2026-05-19T15:05:51.306103+00:00",
      "label": "C24",
      "total_pnl": -429.0,
      "n_positions": 100,
      "sharpe": -16.612,
      "drawdown": 0.0068,
      "win_rate": 0.0
    },
    {
      "ts": "2026-05-19T15:06:51.415349+00:00",
      "label": "C25",
      "total_pnl": -4044.38,
      "n_positions": 52,
      "sharpe": -16.612,
      "drawdown": 0.0068,
      "win_rate": 0.0
    },
    {
      "ts": "2026-05-19T15:07:51.163484+00:00",
      "label": "C26",
      "total_pnl": -3672.58,
      "n_positions": 53,
      "sharpe": -16.612,
      "drawdown": 0.0068,
      "win_rate": 0.0
    },
    {
      "ts": "2026-05-19T15:08:51.160570+00:00",
      "label": "C27",
      "total_pnl": -3068.55,
      "n_positions": 53,
      "sharpe": -16.612,
      "drawdown": 0.0068,
      "win_rate": 0.0
    },
    {
      "ts": "2026-05-19T15:09:51.162181+00:00",
      "label": "C28",
      "total_pnl": -3021.08,
      "n_positions": 53,
      "sharpe": -16.612,
      "drawdown": 0.0068,
      "win_rate": 0.0
    },
    {
      "ts": "2026-05-19T15:10:51.665293+00:00",
      "label": "C29",
      "total_pnl": -3845.67,
      "n_positions": 45,
      "sharpe": -2.2374,
      "drawdown": 0.0022,
      "win_rate": 0.0
    },
    {
      "ts": "2026-05-19T15:11:51.465805+00:00",
      "label": "C30",
      "total_pnl": -3703.86,
      "n_positions": 46,
      "sharpe": -2.2374,
      "drawdown": 0.0022,
      "win_rate": 0.0
    },
    {
      "ts": "2026-05-19T15:12:51.161359+00:00",
      "label": "C31",
      "total_pnl": -1016.42,
      "n_positions": 57,
      "sharpe": -2.2374,
      "drawdown": 0.0022,
      "win_rate": 0.0
    },
    {
      "ts": "2026-05-19T15:13:51.160084+00:00",
      "label": "C32",
      "total_pnl": -3379.19,
      "n_positions": 46,
      "sharpe": -2.2374,
      "drawdown": 0.0022,
      "win_rate": 0.0
    },
    {
      "ts": "2026-05-19T15:14:51.161034+00:00",
      "label": "C33",
      "total_pnl": -3894.62,
      "n_positions": 46,
      "sharpe": -2.2374,
      "drawdown": 0.0022,
      "win_rate": 0.0
    },
    {
      "ts": "2026-05-19T15:15:51.809018+00:00",
      "label": "C34",
      "total_pnl": -4872.84,
      "n_positions": 46,
      "sharpe": -1.3682,
      "drawdown": 0.0015,
      "win_rate": 0.0
    },
    {
      "ts": "2026-05-19T15:16:51.307596+00:00",
      "label": "C35",
      "total_pnl": -5101.79,
      "n_positions": 48,
      "sharpe": -1.3682,
      "drawdown": 0.0015,
      "win_rate": 0.0
    },
    {
      "ts": "2026-05-19T15:17:51.160232+00:00",
      "label": "C36",
      "total_pnl": -5471.09,
      "n_positions": 48,
      "sharpe": 0.0,
      "drawdown": 0.0,
      "win_rate": 0.0
    },
    {
      "ts": "2026-05-19T15:18:51.175931+00:00",
      "label": "C37",
      "total_pnl": -172.77,
      "n_positions": 13,
      "sharpe": 0.0,
      "drawdown": 0.0,
      "win_rate": 0.0
    },
    {
      "ts": "2026-05-19T15:19:51.162241+00:00",
      "label": "C38",
      "total_pnl": -5522.21,
      "n_positions": 48,
      "sharpe": 0.0,
      "drawdown": 0.0,
      "win_rate": 0.0
    },
    {
      "ts": "2026-05-19T15:20:51.398287+00:00",
      "label": "C39",
      "total_pnl": -167.47,
      "n_positions": 100,
      "sharpe": -5.4725,
      "drawdown": 0.0092,
      "win_rate": 0.0
    },
    {
      "ts": "2026-05-19T15:21:51.386841+00:00",
      "label": "C40",
      "total_pnl": -1409.37,
      "n_positions": 59,
      "sharpe": -5.4725,
      "drawdown": 0.0092,
      "win_rate": 0.0
    },
    {
      "ts": "2026-05-19T15:22:51.160284+00:00",
      "label": "C41",
      "total_pnl": -5615.23,
      "n_positions": 49,
      "sharpe": -5.4725,
      "drawdown": 0.0092,
      "win_rate": 0.0
    },
    {
      "ts": "2026-05-19T15:23:51.160101+00:00",
      "label": "C42",
      "total_pnl": -5783.61,
      "n_positions": 49,
      "sharpe": -5.4725,
      "drawdown": 0.0092,
      "win_rate": 0.0
    },
    {
      "ts": "2026-05-19T15:24:51.159793+00:00",
      "label": "C43",
      "total_pnl": -6168.64,
      "n_positions": 49,
      "sharpe": -5.4725,
      "drawdown": 0.0092,
      "win_rate": 0.0
    },
    {
      "ts": "2026-05-19T15:25:51.913184+00:00",
      "label": "C44",
      "total_pnl": -6326.26,
      "n_positions": 49,
      "sharpe": -5.6864,
      "drawdown": 0.0102,
      "win_rate": 0.0
    },
    {
      "ts": "2026-05-19T15:26:51.431536+00:00",
      "label": "C45",
      "total_pnl": -6411.09,
      "n_positions": 51,
      "sharpe": -5.6864,
      "drawdown": 0.0102,
      "win_rate": 0.0
    },
    {
      "ts": "2026-05-19T15:27:51.162456+00:00",
      "label": "C46",
      "total_pnl": -1458.22,
      "n_positions": 67,
      "sharpe": -5.6864,
      "drawdown": 0.0102,
      "win_rate": 0.0
    },
    {
      "ts": "2026-05-19T15:28:51.160342+00:00",
      "label": "C47",
      "total_pnl": -1581.22,
      "n_positions": 67,
      "sharpe": -5.6864,
      "drawdown": 0.0102,
      "win_rate": 0.0
    },
    {
      "ts": "2026-05-19T15:29:51.159855+00:00",
      "label": "C48",
      "total_pnl": -6910.4,
      "n_positions": 51,
      "sharpe": -5.6864,
      "drawdown": 0.0102,
      "win_rate": 0.0
    },
    {
      "ts": "2026-05-19T15:31:51.252183+00:00",
      "label": "C49",
      "total_pnl": -6220.59,
      "n_positions": 45,
      "sharpe": -4.9237,
      "drawdown": 0.0094,
      "win_rate": 0.0
    },
    {
      "label": "C1816",
      "sharpe": 0.0,
      "winrate": 0.5,
      "ts": "2026-05-19T15:32:24.080000+00:00"
    }
  ],
  "max_entries": 30,
  "total_cycles": 1816,
  "updated_at": "2026-05-19T15:32:24.080013+00:00",
  "oracle_cycle": 1816,
  "pushed_from": "oracle_a1_full_pipeline",
  "pushed_at": "2026-05-19T15:32:35.437890+00:00"
}